{
  "beginner": [
    {
      "automation concept": [
        {
          "name": "what is test automation?",
          "description": "description 1",
          "url": "http://google.com",
          "urlLabel": "some urlLabel"
        },
        {
          "name": "what are the benefits of automation?",
          "description": "description something Lorem ipsum",
          "url": "http://google2.com",
          "urlLabel": "some urlLabel2"
        },
        {
          "name": "when to use it?",
          "description": "description3 something Lorem ipsum",
          "url": "http://google3.com",
          "urlLabel": "some urlLabel3"
        }
      ]
    },
    {
      "Git basics": [
        {
          "name": "what is Github/git?",
          "description": "description 1",
          "url": "http://google.com",
          "urlLabel": "some urlLabel"
        },
        {
          "name": "Git branching",
          "description": "Learn Git branching is the most visual and interactive way to learn Git on the web",
          "url": "https://learngitbranching.js.org/",
          "urlLabel": "Git branching"
        },
        {
          "name": "commit/pull request",
          "description": "description something Lorem ipsum",
          "url": "http://google2.com",
          "urlLabel": "some urlLabel2"
        },
        {
          "name": "usage of GUI clients",
          "description": "description3 something Lorem ipsum description3 something Lorem ipsum Some really long description. Check if we can here also, new line is impossible",
          "url": "http://google3.com",
          "urlLabel": "some urlLabel3"
        }
      ]
    },
    {
      "Tool selection": [
        {
          "name": "Postman Beginner's Course - API Testing",
          "description": "This course will introduce you to Postman and is suited for beginners. You will learn how to build API requests with Postman, how to inspect responses and create workflows",
          "url": "https://www.youtube.com/watch?v=VywxIQ2ZXw4”",
          "urlLabel": "postman"
        }
      ]
    },
    {
      "Html & css": [
        {
          "name": "Web elements",
          "description": "In this course, we will use Google Chrome developer tools to look under the hood at the HTML, CSS and JavaScript that make up web pages.",
          "url": "https://testautomationu.applitools.com/web-element-locator-strategies/",
          "urlLabel": "Web elements" 
        }
      ]
    },
    {
      "Terminal": [
        {
          "name": "placeholder",
          "description": "description 1",
          "url": "http://google.com",
          "urlLabel": "some urlLabel"
        }
      ]
    },
    {
      "IDE, Code Editors & plugins": [
        {
          "name": "Visual Studio Code",
          "description": "The most popular source-code editor worldwide (as for 2021). Developed by Microsoft",
          "url": "https://code.visualstudio.com/",
          "urlLabel": "Visual Studio Code main page"
        },
        {
          "name": "Atom",
          "description": "Source code editor developed by GitHub",
          "url": "https://atom.io/",
          "urlLabel": "Atom main page"
        },
        {
          "name": "Sublime Text",
          "description": "Sublime Text is a sophisticated text editor for code, markup and prose",
          "url": "https://sublimetext.com/",
          "urlLabel": "Sublime Text main page"
        },
        {
          "name": "Visual Studio",
          "description": "Full-featured IDE to code, debug, test, and deploy to any platform. Developed by Microsoft",
          "url": "https://visualstudio.microsoft.com/",
          "urlLabel": "Visual Studio main page"
        },
        {
          "name": "WebStorm",
          "description": "WebStorm is an IDE for JavaScript and related technologies, one of many IDE developed by Jetbrains",
          "url": "https://jetbrains.com/webstorm/",
          "urlLabel": "WebStorm main page"
        },
        {
          "name": "IntelliJ IDEA",
          "description": "IntelliJ is an IDE for Java and related technologies (Kotlin for example), one of many IDE developed by Jetbrains",
          "url": "https://jetbrains.com/idea/",
          "urlLabel": "IntelliJ IDEA main page"
        },
        {
          "name": "Eclipse",
          "description": "Eclipse primary use is for developing Java applications, but it may also be used to develop applications in other programming languages",
          "url": "https://eclipse.org/downloads/",
          "urlLabel": "Eclipse main page"
        }
      ]
    }
  ],
  "intermediate": [
    {
      "Automation patterns": [
        {
          "name": "Top Design Patterns",
          "description": "Design Patterns",
          "url": "https://www.devbridge.com/articles/top-design-pattern-test-automation-frameworks/",
          "urlLabel": "Design Patterns"
        },
        {
          "name": "Page Object Models (POM)",
          "description": "Page Object Models",
          "url": "https://medium.com/tech-tajawal/page-object-model-pom-design-pattern-f9588630800b",
          "urlLabel": "Page Object Models"
        },
        {
          "name": "App Actions",
          "description": "App Actions",
          "url": "https://www.cypress.io/blog/2019/01/03/stop-using-page-objects-and-start-using-app-actions/",
          "urlLabel": "App Actions, Cypress"
        },
        {
          "name": "Screenplay Pattern",
          "description": "Screenplay Pattern",
          "url": "https://www.infoq.com/articles/Beyond-Page-Objects-Test-Automation-Serenity-Screenplay/",
          "urlLabel": "Screenplay Pattern"
        }
      ]
    },
    {
      "Javascript & Cypress": [
        {
          "name": "Javascript",
          "description": "Javascript",
          "url": "https://testingjavascript.com/",
          "urlLabel": "Javascript"
        },
        {
          "name": "Cypress Tutorial",
          "description": "UDEMY Cypress Tutorial",
          "url": "https://www.udemy.com/course/cypress-io-master-class/",
          "urlLabel": "Cypress"
        },
        {
          "name": "Cypress Test Automation University Beginner",
          "description": "TAU Cypress Beginner Tutorial",
          "url": "https://testautomationu.applitools.com/cypress-tutorial/",
          "urlLabel": "Cypress"
        },
        {
          "name": "Cypress Test Automation University Advanced",
          "description": "TAU Cypress Advanced Tutorial",
          "url": "https://testautomationu.applitools.com/advanced-cypress-tutorial/",
          "urlLabel": "Cypress"
        },
        {
          "name": "Cypress Tips & Tricks",
          "description": "Cypress Tips & Tricks",
          "url": "https://cypress.tips/",
          "urlLabel": "Cypress"
        }
      ]
    },
    {
      "Java & Selenium": [
        {
          "name": "Java programming",
          "description": "The material covered here is equivalent to the curriculum of a full semester of Java programming at a university and is designed for complete beginners to programming.",
          "url": "https://testautomationu.applitools.com/java-programming-course/",
          "urlLabel": "Java programming"
        }
      ]
    },
    {
      "CI Integration": [
        {
          "name": "placeholder",
          "description": "description 1",
          "url": "http://google.com",
          "urlLabel": "some urlLabel"
        }
      ]
    },
    {
      "BDD": [
        {
          "name": "Gherkin",
          "description": "Gherkin example",
          "url": "https://automationpanda.com/2017/01/27/bdd-101-gherkin-by-example/",
          "urlLabel": "Gherkin"
        },
        {
          "name": "Writing good Gherkin",
          "description": "Gherkin example",
          "url": "https://automationpanda.com/2017/01/30/bdd-101-writing-good-gherkin/",
          "urlLabel": "Gherkin"
        },
        {
          "name": "BDD Tutorial",
          "description": "BDD Tutorial",
          "url": "https://automationpanda.com/2017/01/25/bdd-101-introducing-bdd/",
          "urlLabel": "BDD"
        }
      ]
    },
    {
      "Mobile automation": [
        {
          "name": "Appium",
          "description": "description 1",
          "url": "http://google.com",
          "urlLabel": "some urlLabel"
        }
      ]
    },
    {
      "API automation": [
        {
          "name": "Postman",
          "description": "Postman Learning Center",
          "url": "https://learning.postman.com/docs/getting-started/introduction/",
          "urlLabel": "Postman"
        },
        {
          "name": "Python Requests",
          "description": "Basic Python Requests documentation",
          "url": "https://docs.python-requests.org/en/latest/",
          "urlLabel": "Requests"
        },
        {
          "name": "Python Requests Tutorial",
          "description": "Basic Python Requests tutorial",
          "url": "https://realpython.com/python-requests/",
          "urlLabel": "Requests"
        },
        {
          "name": "REST Assured Tutorial",
          "description": "REST Assured Tutorial",
          "url": "https://www.baeldung.com/rest-assured-tutorial",
          "urlLabel": "REST Assured"
        }
      ]
    }
  ],
  "expert": [
    {
      "Cloud-Based Cross Browser Testing": [
        {
          "name": "placeholder",
          "description": "description 1",
          "url": "http://google.com",
          "urlLabel": "some urlLabel"
        }
      ]
    },
    {
      "Parallel testing": [
        {
          "name": "placeholder",
          "description": "description 1",
          "url": "http://google.com",
          "urlLabel": "some urlLabel"
        }
      ]
    },
    {
      "Cypress - advanced": [
        {
          "name": "placeholder",
          "description": "description 1",
          "url": "http://google.com",
          "urlLabel": "some urlLabel"
        }
      ]
    },
    {
      "Selenium - advanced": [
        {
          "name": "placeholder",
          "description": "description 1",
          "url": "http://google.com",
          "urlLabel": "some urlLabel"
        }
      ]
    }
  ]
}
